[
 {
  "allow_in_quick_entry": 0,
  "allow_on_submit": 1,
  "bold": 0,
  "collapsible": 0,
  "collapsible_depends_on": null,
  "columns": 0,
  "default": null,
  "depends_on": null,
  "description": null,
  "docstatus": 0,
  "doctype": "Custom Field",
  "dt": "Sales Order",
  "fetch_from": null,
  "fetch_if_empty": 0,
  "fieldname": "workflow_state",
  "fieldtype": "Link",
  "hidden": 1,
  "hide_border": 0,
  "hide_days": 0,
  "hide_seconds": 0,
  "ignore_user_permissions": 0,
  "ignore_xss_filter": 0,
  "in_global_search": 0,
  "in_list_view": 0,
  "in_preview": 0,
  "in_standard_filter": 0,
  "insert_after": null,
  "is_system_generated": 0,
  "is_virtual": 0,
  "label": "Workflow State",
  "length": 0,
  "link_filters": null,
  "mandatory_depends_on": null,
  "modified": "2025-05-28 11:58:21.787298",
  "module": null,
  "name": "Sales Order-workflow_state",
  "no_copy": 1,
  "non_negative": 0,
  "options": "Workflow State",
  "permlevel": 0,
  "placeholder": null,
  "precision": "",
  "print_hide": 0,
  "print_hide_if_no_value": 0,
  "print_width": null,
  "read_only": 0,
  "read_only_depends_on": null,
  "report_hide": 0,
  "reqd": 0,
  "search_index": 0,
  "show_dashboard": 0,
  "sort_options": 0,
  "translatable": 0,
  "unique": 0,
  "width": null
 },
 {
  "allow_in_quick_entry": 0,
  "allow_on_submit": 1,
  "bold": 0,
  "collapsible": 0,
  "collapsible_depends_on": null,
  "columns": 0,
  "default": null,
  "depends_on": null,
  "description": null,
  "docstatus": 0,
  "doctype": "Custom Field",
  "dt": "Sales Invoice",
  "fetch_from": null,
  "fetch_if_empty": 0,
  "fieldname": "workflow_state",
  "fieldtype": "Link",
  "hidden": 1,
  "hide_border": 0,
  "hide_days": 0,
  "hide_seconds": 0,
  "ignore_user_permissions": 0,
  "ignore_xss_filter": 0,
  "in_global_search": 0,
  "in_list_view": 0,
  "in_preview": 0,
  "in_standard_filter": 0,
  "insert_after": null,
  "is_system_generated": 0,
  "is_virtual": 0,
  "label": "Workflow State",
  "length": 0,
  "link_filters": null,
  "mandatory_depends_on": null,
  "modified": "2025-05-12 14:17:21.226980",
  "module": null,
  "name": "Sales Invoice-workflow_state",
  "no_copy": 1,
  "non_negative": 0,
  "options": "Workflow State",
  "permlevel": 0,
  "placeholder": null,
  "precision": "",
  "print_hide": 0,
  "print_hide_if_no_value": 0,
  "print_width": null,
  "read_only": 0,
  "read_only_depends_on": null,
  "report_hide": 0,
  "reqd": 0,
  "search_index": 0,
  "show_dashboard": 0,
  "sort_options": 0,
  "translatable": 0,
  "unique": 0,
  "width": null
 },
 {
  "allow_in_quick_entry": 0,
  "allow_on_submit": 0,
  "bold": 0,
  "collapsible": 0,
  "collapsible_depends_on": null,
  "columns": 0,
  "default": null,
  "depends_on": null,
  "description": null,
  "docstatus": 0,
  "doctype": "Custom Field",
  "dt": "POS Field",
  "fetch_from": null,
  "fetch_if_empty": 0,
  "fieldname": "pos_remarks",
  "fieldtype": "Data",
  "hidden": 0,
  "hide_border": 0,
  "hide_days": 0,
  "hide_seconds": 0,
  "ignore_user_permissions": 0,
  "ignore_xss_filter": 0,
  "in_global_search": 0,
  "in_list_view": 0,
  "in_preview": 0,
  "in_standard_filter": 0,
  "insert_after": null,
  "is_system_generated": 0,
  "is_virtual": 0,
  "label": "Remarks",
  "length": 0,
  "link_filters": null,
  "mandatory_depends_on": null,
  "modified": "2025-05-16 20:27:49.178802",
  "module": null,
  "name": "POS Field-custom_remarks",
  "no_copy": 0,
  "non_negative": 0,
  "options": null,
  "permlevel": 0,
  "placeholder": null,
  "precision": "",
  "print_hide": 0,
  "print_hide_if_no_value": 0,
  "print_width": null,
  "read_only": 0,
  "read_only_depends_on": null,
  "report_hide": 0,
  "reqd": 0,
  "search_index": 0,
  "show_dashboard": 0,
  "sort_options": 0,
  "translatable": 0,
  "unique": 0,
  "width": null
 },
 {
  "allow_in_quick_entry": 0,
  "allow_on_submit": 0,
  "bold": 0,
  "collapsible": 0,
  "collapsible_depends_on": null,
  "columns": 0,
  "default": null,
  "depends_on": null,
  "description": null,
  "docstatus": 0,
  "doctype": "Custom Field",
  "dt": "UTM Campaign",
  "fetch_from": null,
  "fetch_if_empty": 0,
  "fieldname": "crm_campaign",
  "fieldtype": "Link",
  "hidden": 0,
  "hide_border": 0,
  "hide_days": 0,
  "hide_seconds": 0,
  "ignore_user_permissions": 0,
  "ignore_xss_filter": 0,
  "in_global_search": 0,
  "in_list_view": 0,
  "in_preview": 0,
  "in_standard_filter": 0,
  "insert_after": "campaign_decription",
  "is_system_generated": 1,
  "is_virtual": 0,
  "label": "Messaging CRM Campagin",
  "length": 0,
  "link_filters": null,
  "mandatory_depends_on": null,
  "modified": "2025-05-29 21:53:26.530090",
  "module": null,
  "name": "UTM Campaign-crm_campaign",
  "no_copy": 0,
  "non_negative": 0,
  "options": "Campaign",
  "permlevel": 0,
  "placeholder": null,
  "precision": "",
  "print_hide": 0,
  "print_hide_if_no_value": 0,
  "print_width": null,
  "read_only": 0,
  "read_only_depends_on": null,
  "report_hide": 0,
  "reqd": 0,
  "search_index": 0,
  "show_dashboard": 0,
  "sort_options": 0,
  "translatable": 0,
  "unique": 0,
  "width": null
 },
 {
  "allow_in_quick_entry": 0,
  "allow_on_submit": 0,
  "bold": 0,
  "collapsible": 0,
  "collapsible_depends_on": null,
  "columns": 0,
  "default": null,
  "depends_on": null,
  "description": null,
  "docstatus": 0,
  "doctype": "Custom Field",
  "dt": "Customer",
  "fetch_from": null,
  "fetch_if_empty": 0,
  "fieldname": "dharma_name",
  "fieldtype": "Data",
  "hidden": 0,
  "hide_border": 0,
  "hide_days": 0,
  "hide_seconds": 0,
  "ignore_user_permissions": 0,
  "ignore_xss_filter": 0,
  "in_global_search": 0,
  "in_list_view": 0,
  "in_preview": 0,
  "in_standard_filter": 0,
  "insert_after": "customer_name",
  "is_system_generated": 0,
  "is_virtual": 0,
  "label": "Dharma Name",
  "length": 0,
  "link_filters": null,
  "mandatory_depends_on": null,
  "modified": "2025-06-02 15:52:34.477218",
  "module": null,
  "name": "Customer-dharma_name",
  "no_copy": 0,
  "non_negative": 0,
  "options": null,
  "permlevel": 0,
  "placeholder": null,
  "precision": "",
  "print_hide": 0,
  "print_hide_if_no_value": 0,
  "print_width": null,
  "read_only": 0,
  "read_only_depends_on": null,
  "report_hide": 0,
  "reqd": 1,
  "search_index": 0,
  "show_dashboard": 0,
  "sort_options": 0,
  "translatable": 0,
  "unique": 0,
  "width": null
 },
 {
  "allow_in_quick_entry": 0,
  "allow_on_submit": 0,
  "bold": 0,
  "collapsible": 0,
  "collapsible_depends_on": null,
  "columns": 0,
  "default": null,
  "depends_on": null,
  "description": null,
  "docstatus": 0,
  "doctype": "Custom Field",
  "dt": "Sales Order Item",
  "fetch_from": null,
  "fetch_if_empty": 0,
  "fieldname": "lighting_location",
  "fieldtype": "Data",
  "hidden": 0,
  "hide_border": 0,
  "hide_days": 0,
  "hide_seconds": 0,
  "ignore_user_permissions": 0,
  "ignore_xss_filter": 0,
  "in_global_search": 0,
  "in_list_view": 0,
  "in_preview": 0,
  "in_standard_filter": 0,
  "insert_after": "col_break1",
  "is_system_generated": 0,
  "is_virtual": 0,
  "label": "Lighting Location",
  "length": 0,
  "link_filters": null,
  "mandatory_depends_on": null,
  "modified": "2025-05-30 17:15:18.031426",
  "module": null,
  "name": "Sales Order Item-lighting_location",
  "no_copy": 0,
  "non_negative": 0,
  "options": null,
  "permlevel": 0,
  "placeholder": null,
  "precision": "",
  "print_hide": 0,
  "print_hide_if_no_value": 0,
  "print_width": null,
  "read_only": 0,
  "read_only_depends_on": null,
  "report_hide": 0,
  "reqd": 0,
  "search_index": 0,
  "show_dashboard": 0,
  "sort_options": 0,
  "translatable": 0,
  "unique": 0,
  "width": null
 },
 {
  "allow_in_quick_entry": 0,
  "allow_on_submit": 0,
  "bold": 0,
  "collapsible": 0,
  "collapsible_depends_on": null,
  "columns": 0,
  "default": null,
  "depends_on": null,
  "description": null,
  "docstatus": 0,
  "doctype": "Custom Field",
  "dt": "Item",
  "fetch_from": null,
  "fetch_if_empty": 0,
  "fieldname": "reminder_duration",
  "fieldtype": "Int",
  "hidden": 0,
  "hide_border": 0,
  "hide_days": 0,
  "hide_seconds": 0,
  "ignore_user_permissions": 0,
  "ignore_xss_filter": 0,
  "in_global_search": 0,
  "in_list_view": 0,
  "in_preview": 0,
  "in_standard_filter": 0,
  "insert_after": "stock_uom",
  "is_system_generated": 0,
  "is_virtual": 0,
  "label": "Reminder Duration",
  "length": 0,
  "link_filters": null,
  "mandatory_depends_on": null,
  "modified": "2025-06-04 17:40:02.407975",
  "module": null,
  "name": "Item-reminder_duration",
  "no_copy": 0,
  "non_negative": 0,
  "options": null,
  "permlevel": 0,
  "placeholder": null,
  "precision": "",
  "print_hide": 0,
  "print_hide_if_no_value": 0,
  "print_width": null,
  "read_only": 0,
  "read_only_depends_on": null,
  "report_hide": 0,
  "reqd": 0,
  "search_index": 0,
  "show_dashboard": 0,
  "sort_options": 0,
  "translatable": 0,
  "unique": 0,
  "width": null
 },
 {
  "allow_in_quick_entry": 0,
  "allow_on_submit": 0,
  "bold": 0,
  "collapsible": 0,
  "collapsible_depends_on": null,
  "columns": 0,
  "default": null,
  "depends_on": null,
  "description": null,
  "docstatus": 0,
  "doctype": "Custom Field",
  "dt": "Customer",
  "fetch_from": null,
  "fetch_if_empty": 0,
  "fieldname": "dob",
  "fieldtype": "Date",
  "hidden": 0,
  "hide_border": 0,
  "hide_days": 0,
  "hide_seconds": 0,
  "ignore_user_permissions": 0,
  "ignore_xss_filter": 0,
  "in_global_search": 0,
  "in_list_view": 0,
  "in_preview": 0,
  "in_standard_filter": 0,
  "insert_after": "customer_group",
  "is_system_generated": 0,
  "is_virtual": 0,
  "label": "Date of Birth",
  "length": 0,
  "link_filters": null,
  "mandatory_depends_on": null,
  "modified": "2025-06-02 16:00:53.476928",
  "module": null,
  "name": "Customer-dob",
  "no_copy": 0,
  "non_negative": 0,
  "options": null,
  "permlevel": 0,
  "placeholder": null,
  "precision": "",
  "print_hide": 0,
  "print_hide_if_no_value": 0,
  "print_width": null,
  "read_only": 0,
  "read_only_depends_on": null,
  "report_hide": 0,
  "reqd": 0,
  "search_index": 0,
  "show_dashboard": 0,
  "sort_options": 0,
  "translatable": 0,
  "unique": 0,
  "width": null
 },
 {
  "allow_in_quick_entry": 0,
  "allow_on_submit": 0,
  "bold": 0,
  "collapsible": 0,
  "collapsible_depends_on": null,
  "columns": 0,
  "default": null,
  "depends_on": null,
  "description": null,
  "docstatus": 0,
  "doctype": "Custom Field",
  "dt": "Sales Order Item",
  "fetch_from": null,
  "fetch_if_empty": 0,
  "fieldname": "start_date",
  "fieldtype": "Date",
  "hidden": 0,
  "hide_border": 0,
  "hide_days": 0,
  "hide_seconds": 0,
  "ignore_user_permissions": 0,
  "ignore_xss_filter": 0,
  "in_global_search": 0,
  "in_list_view": 0,
  "in_preview": 0,
  "in_standard_filter": 0,
  "insert_after": "lighting_location",
  "is_system_generated": 0,
  "is_virtual": 0,
  "label": "Start Date",
  "length": 0,
  "link_filters": null,
  "mandatory_depends_on": null,
  "modified": "2025-05-30 17:15:58.488954",
  "module": null,
  "name": "Sales Order Item-custom_start_date",
  "no_copy": 0,
  "non_negative": 0,
  "options": null,
  "permlevel": 0,
  "placeholder": null,
  "precision": "",
  "print_hide": 0,
  "print_hide_if_no_value": 0,
  "print_width": null,
  "read_only": 0,
  "read_only_depends_on": null,
  "report_hide": 0,
  "reqd": 1,
  "search_index": 0,
  "show_dashboard": 0,
  "sort_options": 0,
  "translatable": 0,
  "unique": 0,
  "width": null
 },
 {
  "allow_in_quick_entry": 0,
  "allow_on_submit": 0,
  "bold": 0,
  "collapsible": 0,
  "collapsible_depends_on": null,
  "columns": 0,
  "default": null,
  "depends_on": null,
  "description": null,
  "docstatus": 0,
  "doctype": "Custom Field",
  "dt": "Sales Order Item",
  "fetch_from": null,
  "fetch_if_empty": 0,
  "fieldname": "additional_information",
  "fieldtype": "Section Break",
  "hidden": 0,
  "hide_border": 0,
  "hide_days": 0,
  "hide_seconds": 0,
  "ignore_user_permissions": 0,
  "ignore_xss_filter": 0,
  "in_global_search": 0,
  "in_list_view": 0,
  "in_preview": 0,
  "in_standard_filter": 0,
  "insert_after": "item_name",
  "is_system_generated": 0,
  "is_virtual": 0,
  "label": "Additional Information",
  "length": 0,
  "link_filters": null,
  "mandatory_depends_on": null,
  "modified": "2025-05-30 17:00:06.520336",
  "module": null,
  "name": "Sales Order Item-custom_additional_information",
  "no_copy": 0,
  "non_negative": 0,
  "options": null,
  "permlevel": 0,
  "placeholder": null,
  "precision": "",
  "print_hide": 0,
  "print_hide_if_no_value": 0,
  "print_width": null,
  "read_only": 0,
  "read_only_depends_on": null,
  "report_hide": 0,
  "reqd": 0,
  "search_index": 0,
  "show_dashboard": 0,
  "sort_options": 0,
  "translatable": 0,
  "unique": 0,
  "width": null
 },
 {
  "allow_in_quick_entry": 0,
  "allow_on_submit": 0,
  "bold": 0,
  "collapsible": 0,
  "collapsible_depends_on": null,
  "columns": 0,
  "default": "1",
  "depends_on": null,
  "description": null,
  "docstatus": 0,
  "doctype": "Custom Field",
  "dt": "Print Settings",
  "fetch_from": null,
  "fetch_if_empty": 0,
  "fieldname": "compact_item_print",
  "fieldtype": "Check",
  "hidden": 0,
  "hide_border": 0,
  "hide_days": 0,
  "hide_seconds": 0,
  "ignore_user_permissions": 0,
  "ignore_xss_filter": 0,
  "in_global_search": 0,
  "in_list_view": 0,
  "in_preview": 0,
  "in_standard_filter": 0,
  "insert_after": "with_letterhead",
  "is_system_generated": 1,
  "is_virtual": 0,
  "label": "Compact Item Print",
  "length": 0,
  "link_filters": null,
  "mandatory_depends_on": null,
  "modified": "2025-04-29 07:53:26.275942",
  "module": null,
  "name": "Print Settings-compact_item_print",
  "no_copy": 0,
  "non_negative": 0,
  "options": null,
  "permlevel": 0,
  "placeholder": null,
  "precision": "",
  "print_hide": 0,
  "print_hide_if_no_value": 0,
  "print_width": null,
  "read_only": 0,
  "read_only_depends_on": null,
  "report_hide": 0,
  "reqd": 0,
  "search_index": 0,
  "show_dashboard": 0,
  "sort_options": 0,
  "translatable": 0,
  "unique": 0,
  "width": null
 },
 {
  "allow_in_quick_entry": 0,
  "allow_on_submit": 0,
  "bold": 0,
  "collapsible": 0,
  "collapsible_depends_on": null,
  "columns": 0,
  "default": null,
  "depends_on": null,
  "description": null,
  "docstatus": 0,
  "doctype": "Custom Field",
  "dt": "Sales Order Item",
  "fetch_from": null,
  "fetch_if_empty": 0,
  "fieldname": "name_on_light",
  "fieldtype": "Data",
  "hidden": 0,
  "hide_border": 0,
  "hide_days": 0,
  "hide_seconds": 0,
  "ignore_user_permissions": 0,
  "ignore_xss_filter": 0,
  "in_global_search": 0,
  "in_list_view": 0,
  "in_preview": 0,
  "in_standard_filter": 0,
  "insert_after": "additional_information",
  "is_system_generated": 0,
  "is_virtual": 0,
  "label": "Name on Light",
  "length": 120,
  "link_filters": null,
  "mandatory_depends_on": null,
  "modified": "2025-05-30 17:00:58.364890",
  "module": null,
  "name": "Sales Order Item-custom_name_on_light",
  "no_copy": 0,
  "non_negative": 0,
  "options": null,
  "permlevel": 0,
  "placeholder": null,
  "precision": "",
  "print_hide": 0,
  "print_hide_if_no_value": 0,
  "print_width": null,
  "read_only": 0,
  "read_only_depends_on": null,
  "report_hide": 0,
  "reqd": 0,
  "search_index": 0,
  "show_dashboard": 0,
  "sort_options": 0,
  "translatable": 0,
  "unique": 0,
  "width": null
 },
 {
  "allow_in_quick_entry": 0,
  "allow_on_submit": 0,
  "bold": 0,
  "collapsible": 0,
  "collapsible_depends_on": null,
  "columns": 0,
  "default": null,
  "depends_on": null,
  "description": null,
  "docstatus": 0,
  "doctype": "Custom Field",
  "dt": "Sales Order Item",
  "fetch_from": null,
  "fetch_if_empty": 0,
  "fieldname": "testing_field",
  "fieldtype": "Data",
  "hidden": 0,
  "hide_border": 0,
  "hide_days": 0,
  "hide_seconds": 0,
  "ignore_user_permissions": 0,
  "ignore_xss_filter": 0,
  "in_global_search": 0,
  "in_list_view": 0,
  "in_preview": 0,
  "in_standard_filter": 0,
  "insert_after": "item_name",
  "is_system_generated": 0,
  "is_virtual": 0,
  "label": "Testing Field",
  "length": 0,
  "link_filters": null,
  "mandatory_depends_on": null,
  "modified": "2025-05-31 00:34:50.720466",
  "module": null,
  "name": "Sales Order Item-testing_field",
  "no_copy": 0,
  "non_negative": 0,
  "options": null,
  "permlevel": 0,
  "placeholder": null,
  "precision": "",
  "print_hide": 0,
  "print_hide_if_no_value": 0,
  "print_width": null,
  "read_only": 0,
  "read_only_depends_on": null,
  "report_hide": 0,
  "reqd": 1,
  "search_index": 0,
  "show_dashboard": 0,
  "sort_options": 0,
  "translatable": 0,
  "unique": 0,
  "width": null
 },
 {
  "allow_in_quick_entry": 0,
  "allow_on_submit": 0,
  "bold": 0,
  "collapsible": 0,
  "collapsible_depends_on": null,
  "columns": 0,
  "default": "0",
  "depends_on": null,
  "description": null,
  "docstatus": 0,
  "doctype": "Custom Field",
  "dt": "Print Settings",
  "fetch_from": null,
  "fetch_if_empty": 0,
  "fieldname": "print_uom_after_quantity",
  "fieldtype": "Check",
  "hidden": 0,
  "hide_border": 0,
  "hide_days": 0,
  "hide_seconds": 0,
  "ignore_user_permissions": 0,
  "ignore_xss_filter": 0,
  "in_global_search": 0,
  "in_list_view": 0,
  "in_preview": 0,
  "in_standard_filter": 0,
  "insert_after": "compact_item_print",
  "is_system_generated": 1,
  "is_virtual": 0,
  "label": "Print UOM after Quantity",
  "length": 0,
  "link_filters": null,
  "mandatory_depends_on": null,
  "modified": "2025-04-29 07:53:26.304233",
  "module": null,
  "name": "Print Settings-print_uom_after_quantity",
  "no_copy": 0,
  "non_negative": 0,
  "options": null,
  "permlevel": 0,
  "placeholder": null,
  "precision": "",
  "print_hide": 0,
  "print_hide_if_no_value": 0,
  "print_width": null,
  "read_only": 0,
  "read_only_depends_on": null,
  "report_hide": 0,
  "reqd": 0,
  "search_index": 0,
  "show_dashboard": 0,
  "sort_options": 0,
  "translatable": 0,
  "unique": 0,
  "width": null
 },
 {
  "allow_in_quick_entry": 0,
  "allow_on_submit": 0,
  "bold": 0,
  "collapsible": 0,
  "collapsible_depends_on": null,
  "columns": 0,
  "default": null,
  "depends_on": null,
  "description": null,
  "docstatus": 0,
  "doctype": "Custom Field",
  "dt": "Sales Order Item",
  "fetch_from": null,
  "fetch_if_empty": 0,
  "fieldname": "date_of_light",
  "fieldtype": "Date",
  "hidden": 0,
  "hide_border": 0,
  "hide_days": 0,
  "hide_seconds": 0,
  "ignore_user_permissions": 0,
  "ignore_xss_filter": 0,
  "in_global_search": 0,
  "in_list_view": 0,
  "in_preview": 0,
  "in_standard_filter": 0,
  "insert_after": "name_on_light",
  "is_system_generated": 0,
  "is_virtual": 0,
  "label": "Date of Light",
  "length": 0,
  "link_filters": null,
  "mandatory_depends_on": null,
  "modified": "2025-05-30 17:02:30.135105",
  "module": null,
  "name": "Sales Order Item-custom_date_of_light",
  "no_copy": 0,
  "non_negative": 0,
  "options": null,
  "permlevel": 0,
  "placeholder": null,
  "precision": "",
  "print_hide": 0,
  "print_hide_if_no_value": 0,
  "print_width": null,
  "read_only": 0,
  "read_only_depends_on": null,
  "report_hide": 0,
  "reqd": 0,
  "search_index": 0,
  "show_dashboard": 0,
  "sort_options": 0,
  "translatable": 0,
  "unique": 0,
  "width": null
 },
 {
  "allow_in_quick_entry": 0,
  "allow_on_submit": 0,
  "bold": 0,
  "collapsible": 0,
  "collapsible_depends_on": null,
  "columns": 0,
  "default": null,
  "depends_on": null,
  "description": null,
  "docstatus": 0,
  "doctype": "Custom Field",
  "dt": "Sales Order Item",
  "fetch_from": null,
  "fetch_if_empty": 0,
  "fieldname": "purpose_of_wish",
  "fieldtype": "Data",
  "hidden": 0,
  "hide_border": 0,
  "hide_days": 0,
  "hide_seconds": 0,
  "ignore_user_permissions": 0,
  "ignore_xss_filter": 0,
  "in_global_search": 0,
  "in_list_view": 0,
  "in_preview": 0,
  "in_standard_filter": 0,
  "insert_after": "date_of_light",
  "is_system_generated": 0,
  "is_virtual": 0,
  "label": "Purpose of Wish",
  "length": 60,
  "link_filters": null,
  "mandatory_depends_on": null,
  "modified": "2025-05-30 17:02:39.697752",
  "module": null,
  "name": "Sales Order Item-custom_purpose_of_wish",
  "no_copy": 0,
  "non_negative": 0,
  "options": null,
  "permlevel": 0,
  "placeholder": null,
  "precision": "",
  "print_hide": 0,
  "print_hide_if_no_value": 0,
  "print_width": null,
  "read_only": 0,
  "read_only_depends_on": null,
  "report_hide": 0,
  "reqd": 0,
  "search_index": 0,
  "show_dashboard": 0,
  "sort_options": 0,
  "translatable": 0,
  "unique": 0,
  "width": null
 },
 {
  "allow_in_quick_entry": 0,
  "allow_on_submit": 0,
  "bold": 0,
  "collapsible": 0,
  "collapsible_depends_on": null,
  "columns": 0,
  "default": null,
  "depends_on": null,
  "description": null,
  "docstatus": 0,
  "doctype": "Custom Field",
  "dt": "Sales Order Item",
  "fetch_from": null,
  "fetch_if_empty": 0,
  "fieldname": "addtional_information_col_break_1",
  "fieldtype": "Column Break",
  "hidden": 0,
  "hide_border": 0,
  "hide_days": 0,
  "hide_seconds": 0,
  "ignore_user_permissions": 0,
  "ignore_xss_filter": 0,
  "in_global_search": 0,
  "in_list_view": 0,
  "in_preview": 0,
  "in_standard_filter": 0,
  "insert_after": "purpose_of_wish",
  "is_system_generated": 0,
  "is_virtual": 0,
  "label": "",
  "length": 0,
  "link_filters": null,
  "mandatory_depends_on": null,
  "modified": "2025-05-30 17:04:00.347593",
  "module": null,
  "name": "Sales Order Item-custom_addtional_information_col_break_1",
  "no_copy": 0,
  "non_negative": 0,
  "options": null,
  "permlevel": 0,
  "placeholder": null,
  "precision": "",
  "print_hide": 0,
  "print_hide_if_no_value": 0,
  "print_width": null,
  "read_only": 0,
  "read_only_depends_on": null,
  "report_hide": 0,
  "reqd": 0,
  "search_index": 0,
  "show_dashboard": 0,
  "sort_options": 0,
  "translatable": 0,
  "unique": 0,
  "width": null
 },
 {
  "allow_in_quick_entry": 0,
  "allow_on_submit": 0,
  "bold": 0,
  "collapsible": 0,
  "collapsible_depends_on": null,
  "columns": 0,
  "default": null,
  "depends_on": null,
  "description": null,
  "docstatus": 0,
  "doctype": "Custom Field",
  "dt": "Sales Order Item",
  "fetch_from": null,
  "fetch_if_empty": 0,
  "fieldname": "home_protector_address",
  "fieldtype": "Data",
  "hidden": 0,
  "hide_border": 0,
  "hide_days": 0,
  "hide_seconds": 0,
  "ignore_user_permissions": 0,
  "ignore_xss_filter": 0,
  "in_global_search": 0,
  "in_list_view": 0,
  "in_preview": 0,
  "in_standard_filter": 0,
  "insert_after": "purpose_of_wish",
  "is_system_generated": 0,
  "is_virtual": 0,
  "label": "Home Protector Address ",
  "length": 0,
  "link_filters": null,
  "mandatory_depends_on": null,
  "modified": "2025-05-30 17:05:23.140697",
  "module": null,
  "name": "Sales Order Item-home_protector_address",
  "no_copy": 0,
  "non_negative": 0,
  "options": null,
  "permlevel": 0,
  "placeholder": null,
  "precision": "",
  "print_hide": 0,
  "print_hide_if_no_value": 0,
  "print_width": null,
  "read_only": 0,
  "read_only_depends_on": null,
  "report_hide": 0,
  "reqd": 0,
  "search_index": 0,
  "show_dashboard": 0,
  "sort_options": 0,
  "translatable": 0,
  "unique": 0,
  "width": null
 },
 {
  "allow_in_quick_entry": 0,
  "allow_on_submit": 0,
  "bold": 0,
  "collapsible": 0,
  "collapsible_depends_on": null,
  "columns": 0,
  "default": null,
  "depends_on": null,
  "description": null,
  "docstatus": 0,
  "doctype": "Custom Field",
  "dt": "Address",
  "fetch_from": null,
  "fetch_if_empty": 0,
  "fieldname": "tax_category",
  "fieldtype": "Link",
  "hidden": 0,
  "hide_border": 0,
  "hide_days": 0,
  "hide_seconds": 0,
  "ignore_user_permissions": 0,
  "ignore_xss_filter": 0,
  "in_global_search": 0,
  "in_list_view": 0,
  "in_preview": 0,
  "in_standard_filter": 0,
  "insert_after": "fax",
  "is_system_generated": 0,
  "is_virtual": 0,
  "label": "Tax Category",
  "length": 0,
  "link_filters": null,
  "mandatory_depends_on": null,
  "modified": "2018-12-28 22:29:21.828090",
  "module": null,
  "name": "Address-tax_category",
  "no_copy": 0,
  "non_negative": 0,
  "options": "Tax Category",
  "permlevel": 0,
  "placeholder": null,
  "precision": "",
  "print_hide": 0,
  "print_hide_if_no_value": 0,
  "print_width": null,
  "read_only": 0,
  "read_only_depends_on": null,
  "report_hide": 0,
  "reqd": 0,
  "search_index": 0,
  "show_dashboard": 0,
  "sort_options": 0,
  "translatable": 0,
  "unique": 0,
  "width": null
 },
 {
  "allow_in_quick_entry": 0,
  "allow_on_submit": 0,
  "bold": 0,
  "collapsible": 0,
  "collapsible_depends_on": null,
  "columns": 0,
  "default": null,
  "depends_on": null,
  "description": null,
  "docstatus": 0,
  "doctype": "Custom Field",
  "dt": "Sales Order Item",
  "fetch_from": null,
  "fetch_if_empty": 0,
  "fieldname": "name_on_the_merit_board",
  "fieldtype": "Data",
  "hidden": 0,
  "hide_border": 0,
  "hide_days": 0,
  "hide_seconds": 0,
  "ignore_user_permissions": 0,
  "ignore_xss_filter": 0,
  "in_global_search": 0,
  "in_list_view": 0,
  "in_preview": 0,
  "in_standard_filter": 0,
  "insert_after": "addtional_information_col_break_1",
  "is_system_generated": 0,
  "is_virtual": 0,
  "label": "Name on the Merit Board",
  "length": 0,
  "link_filters": null,
  "mandatory_depends_on": null,
  "modified": "2025-05-30 17:06:53.055124",
  "module": null,
  "name": "Sales Order Item-name_on_the_merit_board",
  "no_copy": 0,
  "non_negative": 0,
  "options": null,
  "permlevel": 0,
  "placeholder": null,
  "precision": "",
  "print_hide": 0,
  "print_hide_if_no_value": 0,
  "print_width": null,
  "read_only": 0,
  "read_only_depends_on": null,
  "report_hide": 0,
  "reqd": 0,
  "search_index": 0,
  "show_dashboard": 0,
  "sort_options": 0,
  "translatable": 0,
  "unique": 0,
  "width": null
 },
 {
  "allow_in_quick_entry": 0,
  "allow_on_submit": 0,
  "bold": 0,
  "collapsible": 0,
  "collapsible_depends_on": null,
  "columns": 0,
  "default": null,
  "depends_on": null,
  "description": null,
  "docstatus": 0,
  "doctype": "Custom Field",
  "dt": "Sales Order Item",
  "fetch_from": null,
  "fetch_if_empty": 0,
  "fieldname": "days",
  "fieldtype": "Data",
  "hidden": 0,
  "hide_border": 0,
  "hide_days": 0,
  "hide_seconds": 0,
  "ignore_user_permissions": 0,
  "ignore_xss_filter": 0,
  "in_global_search": 0,
  "in_list_view": 0,
  "in_preview": 0,
  "in_standard_filter": 0,
  "insert_after": "name_on_the_merit_board",
  "is_system_generated": 0,
  "is_virtual": 0,
  "label": "Days",
  "length": 0,
  "link_filters": null,
  "mandatory_depends_on": null,
  "modified": "2025-05-30 17:10:22.723503",
  "module": null,
  "name": "Sales Order Item-days",
  "no_copy": 0,
  "non_negative": 0,
  "options": null,
  "permlevel": 0,
  "placeholder": null,
  "precision": "",
  "print_hide": 0,
  "print_hide_if_no_value": 0,
  "print_width": null,
  "read_only": 0,
  "read_only_depends_on": null,
  "report_hide": 0,
  "reqd": 0,
  "search_index": 0,
  "show_dashboard": 0,
  "sort_options": 0,
  "translatable": 0,
  "unique": 0,
  "width": null
 },
 {
  "allow_in_quick_entry": 0,
  "allow_on_submit": 0,
  "bold": 0,
  "collapsible": 0,
  "collapsible_depends_on": null,
  "columns": 0,
  "default": "0",
  "depends_on": null,
  "description": null,
  "docstatus": 0,
  "doctype": "Custom Field",
  "dt": "Print Settings",
  "fetch_from": null,
  "fetch_if_empty": 0,
  "fieldname": "print_taxes_with_zero_amount",
  "fieldtype": "Check",
  "hidden": 0,
  "hide_border": 0,
  "hide_days": 0,
  "hide_seconds": 0,
  "ignore_user_permissions": 0,
  "ignore_xss_filter": 0,
  "in_global_search": 0,
  "in_list_view": 0,
  "in_preview": 0,
  "in_standard_filter": 0,
  "insert_after": "allow_print_for_cancelled",
  "is_system_generated": 1,
  "is_virtual": 0,
  "label": "Print taxes with zero amount",
  "length": 0,
  "link_filters": null,
  "mandatory_depends_on": null,
  "modified": "2025-04-29 07:53:26.332814",
  "module": null,
  "name": "Print Settings-print_taxes_with_zero_amount",
  "no_copy": 0,
  "non_negative": 0,
  "options": null,
  "permlevel": 0,
  "placeholder": null,
  "precision": "",
  "print_hide": 0,
  "print_hide_if_no_value": 0,
  "print_width": null,
  "read_only": 0,
  "read_only_depends_on": null,
  "report_hide": 0,
  "reqd": 0,
  "search_index": 0,
  "show_dashboard": 0,
  "sort_options": 0,
  "translatable": 0,
  "unique": 0,
  "width": null
 },
 {
  "allow_in_quick_entry": 0,
  "allow_on_submit": 0,
  "bold": 0,
  "collapsible": 0,
  "collapsible_depends_on": null,
  "columns": 0,
  "default": "0",
  "depends_on": null,
  "description": null,
  "docstatus": 0,
  "doctype": "Custom Field",
  "dt": "Address",
  "fetch_from": null,
  "fetch_if_empty": 0,
  "fieldname": "is_your_company_address",
  "fieldtype": "Check",
  "hidden": 0,
  "hide_border": 0,
  "hide_days": 0,
  "hide_seconds": 0,
  "ignore_user_permissions": 0,
  "ignore_xss_filter": 0,
  "in_global_search": 0,
  "in_list_view": 0,
  "in_preview": 0,
  "in_standard_filter": 0,
  "insert_after": "linked_with",
  "is_system_generated": 0,
  "is_virtual": 0,
  "label": "Is Your Company Address",
  "length": 0,
  "link_filters": null,
  "mandatory_depends_on": null,
  "modified": "2020-10-14 17:41:40.878179",
  "module": null,
  "name": "Address-is_your_company_address",
  "no_copy": 0,
  "non_negative": 0,
  "options": null,
  "permlevel": 0,
  "placeholder": null,
  "precision": "",
  "print_hide": 0,
  "print_hide_if_no_value": 0,
  "print_width": null,
  "read_only": 0,
  "read_only_depends_on": null,
  "report_hide": 0,
  "reqd": 0,
  "search_index": 0,
  "show_dashboard": 0,
  "sort_options": 0,
  "translatable": 0,
  "unique": 0,
  "width": null
 },
 {
  "allow_in_quick_entry": 0,
  "allow_on_submit": 0,
  "bold": 0,
  "collapsible": 0,
  "collapsible_depends_on": null,
  "columns": 0,
  "default": null,
  "depends_on": null,
  "description": null,
  "docstatus": 0,
  "doctype": "Custom Field",
  "dt": "Contact",
  "fetch_from": null,
  "fetch_if_empty": 0,
  "fieldname": "is_billing_contact",
  "fieldtype": "Check",
  "hidden": 0,
  "hide_border": 0,
  "hide_days": 0,
  "hide_seconds": 0,
  "ignore_user_permissions": 0,
  "ignore_xss_filter": 0,
  "in_global_search": 0,
  "in_list_view": 0,
  "in_preview": 0,
  "in_standard_filter": 0,
  "insert_after": "is_primary_contact",
  "is_system_generated": 0,
  "is_virtual": 0,
  "label": "Is Billing Contact",
  "length": 0,
  "link_filters": null,
  "mandatory_depends_on": null,
  "modified": "2019-12-02 11:00:03.432994",
  "module": null,
  "name": "Contact-is_billing_contact",
  "no_copy": 0,
  "non_negative": 0,
  "options": null,
  "permlevel": 0,
  "placeholder": null,
  "precision": "",
  "print_hide": 0,
  "print_hide_if_no_value": 0,
  "print_width": null,
  "read_only": 0,
  "read_only_depends_on": null,
  "report_hide": 0,
  "reqd": 0,
  "search_index": 0,
  "show_dashboard": 0,
  "sort_options": 0,
  "translatable": 0,
  "unique": 0,
  "width": null
 },
 {
  "allow_in_quick_entry": 0,
  "allow_on_submit": 0,
  "bold": 0,
  "collapsible": 0,
  "collapsible_depends_on": null,
  "columns": 0,
  "default": null,
  "depends_on": null,
  "description": null,
  "docstatus": 0,
  "doctype": "Custom Field",
  "dt": "Sales Order",
  "fetch_from": null,
  "fetch_if_empty": 0,
  "fieldname": "payment_proof",
  "fieldtype": "Attach",
  "hidden": 0,
  "hide_border": 0,
  "hide_days": 0,
  "hide_seconds": 0,
  "ignore_user_permissions": 0,
  "ignore_xss_filter": 0,
  "in_global_search": 0,
  "in_list_view": 0,
  "in_preview": 0,
  "in_standard_filter": 0,
  "insert_after": "pricing_rules",
  "is_system_generated": 0,
  "is_virtual": 0,
  "label": "Payment Proof",
  "length": 0,
  "link_filters": null,
  "mandatory_depends_on": null,
  "modified": "2025-06-02 18:04:35.382296",
  "module": null,
  "name": "Sales Order-payment_proof",
  "no_copy": 0,
  "non_negative": 0,
  "options": null,
  "permlevel": 0,
  "placeholder": null,
  "precision": "",
  "print_hide": 0,
  "print_hide_if_no_value": 0,
  "print_width": null,
  "read_only": 0,
  "read_only_depends_on": null,
  "report_hide": 0,
  "reqd": 0,
  "search_index": 0,
  "show_dashboard": 0,
  "sort_options": 0,
  "translatable": 0,
  "unique": 0,
  "width": null
 }
]